oscar0116655/__init__.py
oscar0116655/print1.py
oscar0116655/print2.py
oscar0116655-1.0.0.dist-info/METADATA
oscar0116655-1.0.0.dist-info/WHEEL
oscar0116655-1.0.0.dist-info/top_level.txt
oscar0116655-1.0.0.dist-info/RECORD
